apispec_plugins/__init__.py
apispec_plugins/base/__init__.py
apispec_plugins/base/mixin.py
apispec_plugins/base/registry.py
apispec_plugins/base/types.py
apispec_plugins/ext/__init__.py
apispec_plugins/ext/pydantic.py
apispec_plugins/utils.py
apispec_plugins/webframeworks/__init__.py
apispec_plugins/webframeworks/flask.py
apispec_plugins-1.1.1.dist-info/LICENSE
apispec_plugins-1.1.1.dist-info/METADATA
apispec_plugins-1.1.1.dist-info/WHEEL
apispec_plugins-1.1.1.dist-info/RECORD
