Metadata-Version: 2.1
Name: apispec-plugins
Version: 1.1.1
Summary: Plugins for apispec
Home-page: https://github.com/codectl/apispec-plugins
License: MIT
Keywords: apispec,plugins,swagger,openapi,oas2,oas3,specification,documentation,spec,rest,api,web,flask,pydantic,python,python3
Author: Renato Damas
Author-email: rena2damas@gmail.com
Requires-Python: >=3.8,<4.0
Classifier: Intended Audience :: Developers
Classifier: License :: OSI Approved :: MIT License
Classifier: Natural Language :: English
Classifier: Programming Language :: Python :: 3
Classifier: Programming Language :: Python :: 3.8
Classifier: Programming Language :: Python :: 3.9
Classifier: Programming Language :: Python :: 3.10
Classifier: Programming Language :: Python :: 3.11
Classifier: Programming Language :: Python :: 3
Classifier: Programming Language :: Python :: 3.10
Classifier: Programming Language :: Python :: 3.11
Classifier: Programming Language :: Python :: 3.8
Classifier: Programming Language :: Python :: 3.9
Provides-Extra: flask
Requires-Dist: apispec[yaml] (>=6.3.0,<7.0.0)
Requires-Dist: flask (>=2.1.3,<3.0.0) ; extra == "flask"
Requires-Dist: pydantic (>=1.10.7,<2.0.0)
Project-URL: Repository, https://github.com/codectl/apispec-plugins
Project-URL: issues, https://github.com/codectl/apispec-plugins/issues
